request_limiter/__init__.py
request_limiter/decorators.py
request_limiter/exceptions.py
request_limiter/strategy.py
request_limiter-0.1.1.dist-info/AUTHORS.rst
request_limiter-0.1.1.dist-info/LICENSE
request_limiter-0.1.1.dist-info/METADATA
request_limiter-0.1.1.dist-info/WHEEL
request_limiter-0.1.1.dist-info/entry_points.txt
request_limiter-0.1.1.dist-info/top_level.txt
request_limiter-0.1.1.dist-info/RECORD
