Metadata-Version: 2.1
Name: request-limiter
Version: 0.1.1
Summary: Request limiter contains a decorator to limit the rate of http request
Home-page: https://github.com/matibek/request_limiter
Author: Mati Bekuma Terefe
Author-email: matibek@gmail.com
License: MIT license
Keywords: request_limiter
Platform: UNKNOWN
Classifier: Development Status :: 2 - Pre-Alpha
Classifier: Intended Audience :: Developers
Classifier: License :: OSI Approved :: MIT License
Classifier: Natural Language :: English
Classifier: Programming Language :: Python :: 3
Classifier: Programming Language :: Python :: 3.6
Classifier: Programming Language :: Python :: 3.7
Classifier: Programming Language :: Python :: 3.8
Requires-Python: >=3.6
